[
  {
    "adjustmentType": "borrowerNumber",
    "data": [
      {
        "creditBracket": 1,
        "ltvRatios": {
          "97": -0.0013,
          "95": -0.0009,
          "90": -0.0007,
          "85": -0.0003
        }
      },
      {
        "creditBracket": 2,
        "ltvRatios": {
          "97": -0.0013,
          "95": -0.0009,
          "90": -0.0007,
          "85": -0.0003
        }
      },
      {
        "creditBracket": 3,
        "ltvRatios": {
          "97": -0.0013,
          "95": -0.0009,
          "90": -0.0007,
          "85": -0.0003
        }
      },
      {
        "creditBracket": 4,
        "ltvRatios": {
          "97": -0.0013,
          "95": -0.0010,
          "90": -0.0007,
          "85": -0.0003
        }
      },
      {
        "creditBracket": 5,
        "ltvRatios": {
          "97": -0.0014,
          "95": -0.0011,
          "90": -0.0008,
          "85": -0.0003
        }
      },
      {
        "creditBracket": 6,
        "ltvRatios": {
          "97": -0.0015,
          "95": -0.0012,
          "90": -0.0009,
          "85": -0.0003
        }
      },
      {
        "creditBracket": 7,
        "ltvRatios": {
          "97": -0.0016,
          "95": -0.0014,
          "90": -0.0009,
          "85": -0.0003
        }
      },
      {
        "creditBracket": 8,
        "ltvRatios": {
          "97": -0.0018,
          "95": -0.0016,
          "90": -0.0010,
          "85": -0.0004
        }
      }
    ]
  },
  {
    "adjustmentType": "borrowerDti",
    "data": [
      {
        "creditBracket": 1,
        "ltvRatios": {
          "97": 0.0010,
          "95": 0.0009,
          "90": 0.0007,
          "85": 0.0003
        }
      },
      {
        "creditBracket": 2,
        "ltvRatios": {
          "97": 0.0014,
          "95": 0.0011,
          "90": 0.0010,
          "85": 0.0004
        }
      },
      {
        "creditBracket": 3,
        "ltvRatios": {
          "97": 0.0017,
          "95": 0.0014,
          "90": 0.0012,
          "85": 0.0005
        }
      },
      {
        "creditBracket": 4,
        "ltvRatios": {
          "97": 0.0021,
          "95": 0.0018,
          "90": 0.0015,
          "85": 0.0005
        }
      },
      {
        "creditBracket": 5,
        "ltvRatios": {
          "97": 0.0026,
          "95": 0.0023,
          "90": 0.0019,
          "85": 0.0007
        }
      },
      {
        "creditBracket": 6,
        "ltvRatios": {
          "97": 0.0035,
          "95": 0.0027,
          "90": 0.0021,
          "85": 0.0009
        }
      },
      {
        "creditBracket": 7,
        "ltvRatios": {
          "97": 0.0037,
          "95": 0.0029,
          "90": 0.0023,
          "85": 0.0009
        }
      },
      {
        "creditBracket": 8,
        "ltvRatios": {
          "97": 0.0038,
          "95": 0.0031,
          "90": 0.0024,
          "85": 0.0009
        }
      }
    ]
  }
]
